MANIFEST.in
README.rst
setup.cfg
setup.py
src/simoorg/Journal.py
src/simoorg/Logger.py
src/simoorg/__init__.py
src/simoorg/__main__.py
src/simoorg/atropos.py
src/simoorg/moirai.py
src/simoorg.egg-info/PKG-INFO
src/simoorg.egg-info/SOURCES.txt
src/simoorg.egg-info/dependency_links.txt
src/simoorg.egg-info/entry_points.txt
src/simoorg.egg-info/requires.txt
src/simoorg.egg-info/top_level.txt
src/simoorg/Api/ApiConstants.py
src/simoorg/Api/MoiraiApiServer.py
src/simoorg/Api/__init__.py
src/simoorg/plugins/__init__.py
src/simoorg/plugins/common/ZKUtil.py
src/simoorg/plugins/common/__init__.py
src/simoorg/plugins/handler/BaseHandler.py
src/simoorg/plugins/handler/__init__.py
src/simoorg/plugins/handler/ShellScriptHandler/ShellScriptHandler.py
src/simoorg/plugins/handler/ShellScriptHandler/__init__.py
src/simoorg/plugins/handler/TestHandler/TestHandler.py
src/simoorg/plugins/handler/TestHandler/__init__.py
src/simoorg/plugins/healthcheck/HealthCheck.py
src/simoorg/plugins/healthcheck/__init__.py
src/simoorg/plugins/healthcheck/DefaultHealthCheck/DefaultHealthCheck.py
src/simoorg/plugins/healthcheck/DefaultHealthCheck/__init__.py
src/simoorg/plugins/healthcheck/KafkaHealthCheck/KafkaHealthCheck.py
src/simoorg/plugins/healthcheck/KafkaHealthCheck/__init__.py
src/simoorg/plugins/scheduler/BaseScheduler.py
src/simoorg/plugins/scheduler/__init__.py
src/simoorg/plugins/scheduler/NonDeterministicScheduler/NonDeterministicScheduler.py
src/simoorg/plugins/scheduler/NonDeterministicScheduler/__init__.py
src/simoorg/plugins/scheduler/TestScheduler/TestScheduler.py
src/simoorg/plugins/scheduler/TestScheduler/__init__.py
src/simoorg/plugins/topology/TopologyBuilder.py
src/simoorg/plugins/topology/__init__.py
src/simoorg/plugins/topology/KafkaTopology/KafkaTopology.py
src/simoorg/plugins/topology/KafkaTopology/MetaData.py
src/simoorg/plugins/topology/KafkaTopology/__init__.py
src/simoorg/plugins/topology/StaticTopology/StaticTopology.py
src/simoorg/plugins/topology/StaticTopology/__init__.py
src/simoorg/plugins/topology/TestTopology/TestTopology.py
src/simoorg/plugins/topology/TestTopology/__init__.py