Metadata-Version: 1.0
Name: simoorg
Version: 0.0.1
Summary: UNKNOWN
Home-page: http://github.com/linkedin/simoorg
Author: Tofig Suleymanov
Author-email: TBD
License: Apache
Download-URL: https://github.com/linkedin/simoorg/tarball/0.2.2
Platform: UNKNOWN
Classifier: Intended Audience :: Developers
Classifier: License :: OSI Approved :: Apache Software License
Classifier: Programming Language :: Python
Classifier: Programming Language :: Python :: 2.6
Classifier: Programming Language :: Python :: 2.7
Classifier: Programming Language :: Python :: 3
Classifier: Programming Language :: Python :: 3.3
